pydise/__init__.py
pydise/detector.py
tests/__init__.py
tests/test_base.py
tests/test_conditionals.py
tests/test_statements.py
pydise-0.0.5.dist-info/LICENSE
pydise-0.0.5.dist-info/METADATA
pydise-0.0.5.dist-info/WHEEL
pydise-0.0.5.dist-info/entry_points.txt
pydise-0.0.5.dist-info/top_level.txt
pydise-0.0.5.dist-info/RECORD
