Metadata-Version: 2.1
Name: pydise
Version: 0.0.5
Summary: Detection of file that generate side effects when imported.
Home-page: https://github.com/Hwoahwoa/pydise
Author: Hwoahwoa
Author-email: hwoahwoa@protonmail.com
Keywords: python,import,side-effect
Classifier: Programming Language :: Python :: 3
Classifier: License :: OSI Approved :: MIT License
Classifier: Operating System :: OS Independent
Requires-Python: >=3.9
License-File: LICENSE
